PySAM_DAOTk/AdjustmentFactors.cpython-35m-x86_64-linux-gnu.so
PySAM_DAOTk/Annualoutput.cpython-35m-x86_64-linux-gnu.so
PySAM_DAOTk/Battery.cpython-35m-x86_64-linux-gnu.so
PySAM_DAOTk/BatteryStateful.cpython-35m-x86_64-linux-gnu.so
PySAM_DAOTk/BatteryTools.py
PySAM_DAOTk/Battwatts.cpython-35m-x86_64-linux-gnu.so
PySAM_DAOTk/Belpe.cpython-35m-x86_64-linux-gnu.so
PySAM_DAOTk/Biomass.cpython-35m-x86_64-linux-gnu.so
PySAM_DAOTk/Cashloan.cpython-35m-x86_64-linux-gnu.so
PySAM_DAOTk/CbConstructionFinancing.cpython-35m-x86_64-linux-gnu.so
PySAM_DAOTk/CbEmpiricalHceHeatLoss.cpython-35m-x86_64-linux-gnu.so
PySAM_DAOTk/CbMsptSystemCosts.cpython-35m-x86_64-linux-gnu.so
PySAM_DAOTk/DsgFluxPreprocess.cpython-35m-x86_64-linux-gnu.so
PySAM_DAOTk/Equpartflip.cpython-35m-x86_64-linux-gnu.so
PySAM_DAOTk/Fuelcell.cpython-35m-x86_64-linux-gnu.so
PySAM_DAOTk/GenericSystem.cpython-35m-x86_64-linux-gnu.so
PySAM_DAOTk/Geothermal.cpython-35m-x86_64-linux-gnu.so
PySAM_DAOTk/GeothermalCosts.cpython-35m-x86_64-linux-gnu.so
PySAM_DAOTk/Grid.cpython-35m-x86_64-linux-gnu.so
PySAM_DAOTk/Hcpv.cpython-35m-x86_64-linux-gnu.so
PySAM_DAOTk/HostDeveloper.cpython-35m-x86_64-linux-gnu.so
PySAM_DAOTk/Iec61853interp.cpython-35m-x86_64-linux-gnu.so
PySAM_DAOTk/Iec61853par.cpython-35m-x86_64-linux-gnu.so
PySAM_DAOTk/InvCecCg.cpython-35m-x86_64-linux-gnu.so
PySAM_DAOTk/IphToLcoefcr.cpython-35m-x86_64-linux-gnu.so
PySAM_DAOTk/Ippppa.cpython-35m-x86_64-linux-gnu.so
PySAM_DAOTk/Irradproc.cpython-35m-x86_64-linux-gnu.so
PySAM_DAOTk/IsccDesignPoint.cpython-35m-x86_64-linux-gnu.so
PySAM_DAOTk/Layoutarea.cpython-35m-x86_64-linux-gnu.so
PySAM_DAOTk/Lcoefcr.cpython-35m-x86_64-linux-gnu.so
PySAM_DAOTk/Levpartflip.cpython-35m-x86_64-linux-gnu.so
PySAM_DAOTk/LinearFresnelDsgIph.cpython-35m-x86_64-linux-gnu.so
PySAM_DAOTk/Merchantplant.cpython-35m-x86_64-linux-gnu.so
PySAM_DAOTk/MhkCosts.cpython-35m-x86_64-linux-gnu.so
PySAM_DAOTk/MhkTidal.cpython-35m-x86_64-linux-gnu.so
PySAM_DAOTk/MhkWave.cpython-35m-x86_64-linux-gnu.so
NREL_PySAM_DAO_Tk-1.3.3.dist-info/LICENSE
NREL_PySAM_DAO_Tk-1.3.3.dist-info/METADATA
NREL_PySAM_DAO_Tk-1.3.3.dist-info/WHEEL
NREL_PySAM_DAO_Tk-1.3.3.dist-info/top_level.txt
NREL_PySAM_DAO_Tk-1.3.3.dist-info/RECORD
